imgflippy/__init__.py
imgflippy/__main__.py
imgflippy/config.py
imgflippy/data.py
imgflippy/model.py
imgflippy/utils.py
imgflippy-0.0.3.dist-info/LICENSE
imgflippy-0.0.3.dist-info/METADATA
imgflippy-0.0.3.dist-info/WHEEL
imgflippy-0.0.3.dist-info/top_level.txt
imgflippy-0.0.3.dist-info/RECORD
