Metadata-Version: 2.1
Name: imgflippy
Version: 0.0.3
Summary: An open source Python wrapper for the imgflip RESTful API (https://api.imgflip.com).
Home-page: https://github.com/theceebee/pyimgflip
Author: Caleb Bell
Author-email: caleb@theceebee.com
License: UNKNOWN
Keywords: imgflip meme API
Platform: UNKNOWN
Classifier: Development Status :: 3 - Alpha
Classifier: Intended Audience :: Developers
Classifier: License :: OSI Approved :: GNU Lesser General Public License v3 (LGPLv3)
Classifier: Natural Language :: English
Classifier: Programming Language :: Python :: 2.7
Classifier: Programming Language :: Python :: 3
Requires-Python: >=2.7
Requires-Dist: requests
Requires-Dist: six
